tinyscpi/__init__.py
tinyscpi/helpers.py
tinyscpi/run.py
tinyscpi/scpi_functional.py
tinyscpi/scpi_parser.py
tinyscpi/tinySCPI.py
tinyscpi/dictionaries/__init__.py
tinyscpi/dictionaries/digit_mappings_dict.py
tinyscpi/dictionaries/scpi_cmds_mapped_to_funcs_dict.py
tinyscpi/dictionaries/scpi_lookup_dict.py
tinyscpi/dictionaries/scpi_valid_dict.py
tinyscpi/tests/__init__.py
tinyscpi/tests/test_scpi_functional.py
tinyscpi/tests/test_scpi_parser.py
tinyscpi-1.0.1.dist-info/LICENSE.txt
tinyscpi-1.0.1.dist-info/METADATA
tinyscpi-1.0.1.dist-info/WHEEL
tinyscpi-1.0.1.dist-info/top_level.txt
tinyscpi-1.0.1.dist-info/RECORD
