Metadata-Version: 2.1
Name: tinyscpi
Version: 1.0.1
Summary: An interface that enables the use of SCPI commands for the tinySA
Author: tinySCPI Team
Author-email: <rndonovan1@gmail.com>
Keywords: python,scpi,interface,commands
Classifier: Development Status :: 3 - Alpha
Classifier: Intended Audience :: Education
Classifier: Programming Language :: Python :: 3
Classifier: Operating System :: Unix
Classifier: Operating System :: MacOS :: MacOS X
Classifier: Operating System :: Microsoft :: Windows
License-File: LICENSE.txt
Requires-Dist: numpy
Requires-Dist: pillow
Requires-Dist: wheel
Requires-Dist: setuptools
Requires-Dist: pyserial
